{
    "roles": [
        {
            "name": "Project Lead",
            "section": "lead"
        },
        {
            "name": "Artists",
            "section": "artists"
        },
        {
            "name": "Developers",
            "section": "developers"
        }
    ],
    "lead": [
        {
            "name": "Finarael",
            "image": "finarael.png"
        }
    ],
    "artists": [
        {
            "name": "Spook",
            "image": "spook.png"
        },
        {
            "name": "Jahgyong",
            "image": "jahgyong.png"
        },
        {
            "name": "Zmays",
            "image": "zmays.png"
        },
        {
            "name": "AtomicReih",
            "image": "atomicreih.png"
        },
        {
            "name": "RoseGhostea",
            "image": "roseghostea.png"
        },
        {
            "name": "Pafufufun",
            "image": "pafufufun.png"
        },
        {
            "name": "Raisins0up",
            "image": "raisins0up.png"
        },
        {
            "name": "Aether",
            "image": "aether.png"
        },
        {
            "name": "Hioko",
            "image": "hioko.png"
        },
        {
            "name": "genieart",
            "image": "genie-art.png"
        },
        {
            "name": "Leo Stone",
            "image": "leo-stone.png"
        },
        {
            "name": "natsu",
            "image": "natsu.png"
        },
        {
            "name": "r4bbit",
            "image": "r4bbit.png"
        },
        {
            "name": "Saku",
            "image": "saku.png"
        },
        {
            "name": "Skellitea",
            "image": "skellitea.png"
        },
        {
            "name": "Socktoebathtub",
            "image": "socktoebathtub.png"
        }
    ],
    "developers": [
        {
            "name": "GlitchTech",
            "image": "glitchtech.png"
        }
    ]
}